d2cd/__init__.py
d2cd/banner.py
d2cd/cli.py
d2cd/config_loader.py
d2cd/main.py
d2cd/utils/__init__.py
d2cd/utils/docker_compose_utils.py
d2cd/utils/errors.py
d2cd/utils/git_utils.py
d2cd/utils/logger.py
d2cd-0.0.3b0.dist-info/METADATA
d2cd-0.0.3b0.dist-info/WHEEL
d2cd-0.0.3b0.dist-info/entry_points.txt
d2cd-0.0.3b0.dist-info/top_level.txt
d2cd-0.0.3b0.dist-info/RECORD
