Metadata-Version: 2.1
Name: d2cd
Version: 0.0.3b0
Summary: Docker Compose Continuous Delivery
Home-page: https://github.com/veerendra2/d2cd
Download-URL: https://github.com/veerendra2/d2cd/archive/0.0.3-beta.tar.gz
Author: veerendra2
Author-email: veerendra2@github.com
License: MIT
Project-URL: Changelog, https://github.com/veerendra2/d2cd/blob/master/CHANGELOG.md
Project-URL: Documentation, https://d2cd.readthedocs.io/en/latest/
Keywords: gitops,cicd,docker-compose,continuous delivery
Classifier: Development Status :: 4 - Beta
Classifier: Intended Audience :: System Administrators
Classifier: License :: OSI Approved :: MIT License
Classifier: Natural Language :: English
Classifier: Operating System :: POSIX :: Linux
Classifier: Programming Language :: Python
Classifier: Programming Language :: Python :: 3
Classifier: Programming Language :: Python :: 3 :: Only
Classifier: Programming Language :: Python :: 3.9
Classifier: Programming Language :: Python :: 3.10
Classifier: Programming Language :: Python :: 3.11
Classifier: Programming Language :: Python :: 3.12
Classifier: Programming Language :: Python :: 3.13
Classifier: Topic :: Utilities
Requires-Python: >=3.9
Requires-Dist: GitPython ==3.1.43
Requires-Dist: loguru ==0.7.2
Requires-Dist: marshmallow ==3.21.1
Requires-Dist: python-on-whales ==0.71.0
Requires-Dist: giturlparse ==0.12.0
Requires-Dist: yamllint ==1.33.0
